edaplotting/__init__.py
edaplotting-0.7.dist-info/DESCRIPTION.rst
edaplotting-0.7.dist-info/METADATA
edaplotting-0.7.dist-info/RECORD
edaplotting-0.7.dist-info/WHEEL
edaplotting-0.7.dist-info/metadata.json
edaplotting-0.7.dist-info/top_level.txt
