Metadata-Version: 2.0
Name: edaplotting
Version: 0.7
Summary: plotting for exploratory data analysis
Home-page: http://github.com/asela1982/edaplotting
Author: Asela Dassanayake
Author-email: asela.d82@gmail.com
License: MIT
Platform: UNKNOWN
